pySMART/__init__.py
pySMART/device.py
pySMART/device_list.py
pySMART/smartctl.py
pySMART/testentry.py
pySMART/utils.py
pySMART/version.py
pySMART/interface/__init__.py
pySMART/interface/common.py
pySMART/interface/ata/__init__.py
pySMART/interface/ata/attribute.py
pySMART/interface/nvme/__init__.py
pySMART/interface/scsi/__init__.py
pySMART/interface/scsi/diagnostics.py
pySMART-1.4.1.dist-info/LICENSE
pySMART-1.4.1.dist-info/METADATA
pySMART-1.4.1.dist-info/WHEEL
pySMART-1.4.1.dist-info/top_level.txt
pySMART-1.4.1.dist-info/RECORD
