Metadata-Version: 2.2
Name: pySMART
Version: 1.4.1
Summary: Wrapper for smartctl (smartmontools)
Author-email: Rafael Leira <rafael.leira@naudit.es>, Marc Herndon <Herndon.MarcT@gmail.com>
License: GNU LGPLv2.1
Project-URL: Homepage, https://github.com/truenas/py-SMART
Classifier: Development Status :: 5 - Production/Stable
Classifier: Intended Audience :: Developers
Classifier: License :: OSI Approved :: GNU Lesser General Public License v2 or later (LGPLv2+)
Classifier: Operating System :: OS Independent
Classifier: Programming Language :: Python
Classifier: Programming Language :: Python :: 3
Classifier: Topic :: Software Development
Classifier: Topic :: Software Development :: Libraries
Classifier: Topic :: Software Development :: Libraries :: Python Modules
Requires-Python: >=3.8
License-File: LICENSE
Requires-Dist: chardet
Requires-Dist: humanfriendly
Provides-Extra: dev
Requires-Dist: pytest; extra == "dev"
Requires-Dist: pytest-cov; extra == "dev"
Requires-Dist: coveralls; extra == "dev"
Requires-Dist: pdoc; extra == "dev"
